Q1/NextPClogic.v
module NextPClogic(NextPC, CurrentPC, SignExtImm64, Branch, ALUZero, Uncondbranch); 
	input [63:0] CurrentPC, SignExtImm64;
	input Branch, ALUZero, Uncondbranch;
	output reg [63:0] NextPC;

	always@(*) begin
		if (Branch || Uncondbranch) 
		begin
			if(ALUZero && Branch || ALUZero && Uncondbranch)
				NextPC <= CurrentPC + (SignExtImm64 << 2);
			else NextPC <= CurrentPC + 4;
		end
		// else if (Uncondbranch) begin
		// 	NextPC <= CurrentPC + (SignExtImm64 << 2);
		// end
		else NextPC <= CurrentPC + 4;
	end
endmodule

Q1/NextPClogicTest.v
`timescale 1ns / 1ps

////////////////////////////////////////////////////////////////////////////////
// Company: 
// Engineer:
//
// Create Date:   15:06:33 03/02/2009
// Design Name:   Decode24
// Module Name:   E:/350/Lab6/Decode24/Decode24Test.v
// Project Name:  Decode24
// Target Device:  
// Tool versions:  
// Description: 
//
// Verilog Test Fixture created by ISE for module: Decode24
//
// Dependencies:
// 
// Revision:
// Revision 0.01 - File Created
// Additional Comments:
// 
////////////////////////////////////////////////////////////////////////////////

`define STRLEN 15
module NextPClogicTest_v;
	initial //This initial block used to dump all wire/reg values to dump file
     begin
       $dumpfile("NextPClogicTest.vcd");
       $dumpvars(0, NextPClogicTest_v);
     end

	task passTest;
		input [3:0] actualOut, expectedOut;
		input [`STRLEN*8:0] testType;
		inout [7:0] passed;
	
		if(actualOut == expectedOut) begin $display ("%s passed", testType); passed = passed + 1; end
		else $display ("%s failed: %d should be %d", testType, actualOut, expectedOut);
	endtask
	
	task allPassed;
		input [7:0] passed;
		input [7:0] numTests;
		
		if(passed == numTests) $display ("All tests passed");
		else $display("Some tests failed");
	endtask
	
	// Inputs
	reg [63:0] CurrentPC;
	reg [63:0] SignExtImm64;
    reg Branch;
    reg ALUZero;
    reg Uncondbranch;
   	reg [7:0] passed;

	// Outputs
	wire [63:0] NextPC;

	// Instantiate the Unit Under Test (UUT)
	NextPClogic uut (
		.CurrentPC(CurrentPC), 
		.SignExtImm64(SignExtImm64),
        .Branch(Branch),
        .ALUZero(ALUZero),
        .Uncondbranch(Uncondbranch),
        .NextPC(NextPC)
	);

	initial begin
		// Initialize Inputs
		CurrentPC = 0;
		SignExtImm64 = 2;
        passed=0;

        Branch = 0;
        ALUZero=0;
        Uncondbranch=0;
   	    // Branch is true if the current instruction is a conditional branch instruction.
        // Uncond branch is true if the current instruction is a Uncond branch instruction

		// Add stimulus here
		#90; Branch = 0; Uncondbranch = 0; ALUZero = 0; #10; passTest(NextPC, 4, "Input 0", passed);
		#90; Branch = 0; Uncondbranch = 0; ALUZero = 1; #10; passTest(NextPC, 4, "Input 1", passed);

		#90; Branch = 0; Uncondbranch = 1; ALUZero = 0; #10; passTest(NextPC, 4, "Input 2", passed);
		#90; Branch = 0; Uncondbranch = 1; ALUZero = 1; #10; passTest(NextPC, 4'b1000, "Input 3", passed);
		
        #90; Branch = 1; Uncondbranch = 0; ALUZero = 0; #10; passTest(NextPC, 4, "Input 4", passed);
		#90; Branch = 1; Uncondbranch = 0; ALUZero = 1; #10; passTest(NextPC, 4'b1000, "Input 5", passed);
		
        #90; Branch = 1; Uncondbranch = 1; ALUZero = 0; #10; passTest(NextPC, 4, "Input 6", passed);
		#90; Branch = 1; Uncondbranch = 1; ALUZero = 1; #10; passTest(NextPC, 4'b1000, "Input 7", passed);

		#90;
		
		allPassed(passed, 8);

	end
      
endmodule

Q1/NextPClogicTest.vcd
$date
	Thu Nov  2 15:41:04 2023
$end
$version
	Icarus Verilog
$end
$timescale
	1ps
$end
$scope module NextPClogicTest_v $end
$var wire 64 ! NextPC [63:0] $end
$var reg 1 " ALUZero $end
$var reg 1 # Branch $end
$var reg 64 $ CurrentPC [63:0] $end
$var reg 64 % SignExtImm64 [63:0] $end
$var reg 1 & Uncondbranch $end
$var reg 8 ' passed [7:0] $end
$scope module uut $end
$var wire 1 " ALUZero $end
$var wire 1 # Branch $end
$var wire 64 ( CurrentPC [63:0] $end
$var wire 64 ) SignExtImm64 [63:0] $end
$var wire 1 & Uncondbranch $end
$var reg 64 * NextPC [63:0] $end
$upscope $end
$scope task allPassed $end
$var reg 8 + numTests [7:0] $end
$var reg 8 , passed [7:0] $end
$upscope $end
$scope task passTest $end
$var reg 4 - actualOut [3:0] $end
$var reg 4 . expectedOut [3:0] $end
$var reg 8 / passed [7:0] $end
$var reg 121 0 testType [120:0] $end
$upscope $end
$upscope $end
$enddefinitions $end
#0
$dumpvars
bx 0
bx /
bx .
bx -
bx ,
bx +
b100 *
b10 )
b0 (
b0 '
0&
b10 %
b0 $
0#
0"
b100 !
$end
#100000
b1 '
b1 /
b1001001011011100111000001110101011101000010000000110000 0
b100 .
b100 -
#190000
1"
#200000
b10 '
b10 /
b1001001011011100111000001110101011101000010000000110001 0
#290000
0"
1&
#300000
b11 '
b11 /
b1001001011011100111000001110101011101000010000000110010 0
#390000
b1000 !
b1000 *
1"
#400000
b100 '
b100 /
b1001001011011100111000001110101011101000010000000110011 0
b1000 .
b1000 -
#490000
b100 !
b100 *
0"
0&
1#
#500000
b101 '
b101 /
b1001001011011100111000001110101011101000010000000110100 0
b100 .
b100 -
#590000
b1000 !
b1000 *
1"
#600000
b110 '
b110 /
b1001001011011100111000001110101011101000010000000110101 0
b1000 .
b1000 -
#690000
b100 !
b100 *
0"
1&
#700000
b111 '
b111 /
b1001001011011100111000001110101011101000010000000110110 0
b100 .
b100 -
#790000
b1000 !
b1000 *
1"
#800000
b1000 '
b1000 /
b1001001011011100111000001110101011101000010000000110111 0
b1000 .
b1000 -
#890000
b1000 +
b1000 ,
